forebit_py/__init__.py
forebit_py/client.py
forebit_py/exceptions.py
forebit_py/resources/customers.py
forebit_py/resources/payments.py
forebit_py/resources/wallets.py
forebit_py/types.py
forebit-0.1.2.dist-info/METADATA
forebit-0.1.2.dist-info/WHEEL
forebit-0.1.2.dist-info/licenses/LICENSE
forebit-0.1.2.dist-info/RECORD
