Metadata-Version: 2.4
Name: forebit
Version: 0.1.2
Summary: Lightweight Python SDK for the Forebit API
License-File: LICENSE
Author: Alex
Author-email: a.marshall@tutamail.com
Requires-Python: >=3.8
Classifier: Programming Language :: Python :: 3
Classifier: Programming Language :: Python :: 3.8
Classifier: Programming Language :: Python :: 3.9
Classifier: Programming Language :: Python :: 3.10
Classifier: Programming Language :: Python :: 3.11
Classifier: Programming Language :: Python :: 3.12
Classifier: Programming Language :: Python :: 3.13
Classifier: Programming Language :: Python :: 3.14
Requires-Dist: aiohttp (>=3.8.0,<4.0.0)
